portfolio_allocation/__init__.py
portfolio_allocation/cache.py
portfolio_allocation/cli.py
portfolio_allocation/gnucash.py
portfolio_allocation/instruments/__init__.py
portfolio_allocation/instruments/instruments.py
portfolio_allocation/instruments/model.py
portfolio_allocation/instruments/sources/__init__.py
portfolio_allocation/instruments/sources/currencies.py
portfolio_allocation/instruments/sources/custom.py
portfolio_allocation/instruments/sources/funds.py
portfolio_allocation/instruments/sources/securities.py
portfolio_allocation/report/__init__.py
portfolio_allocation/report/report.py
portfolio_allocation/report/resources/__init__.py
portfolio_allocation/report/resources/main.css
portfolio_allocation/report/resources/main.js
portfolio_allocation/report/resources/report_template.html
portfolio_allocation-0.3.12.dist-info/LICENSE
portfolio_allocation-0.3.12.dist-info/METADATA
portfolio_allocation-0.3.12.dist-info/WHEEL
portfolio_allocation-0.3.12.dist-info/entry_points.txt
portfolio_allocation-0.3.12.dist-info/RECORD
