Metadata-Version: 2.1
Name: portfolio-allocation
Version: 0.3.12
Summary: Calculates currency, country and industry allocations for portfolio of ETFs and mutual funds
Home-page: https://pypi.org/project/portfolio-allocation/
License: GPL-3.0-or-later
Keywords: etf,allocation,moex,tinkoff,finex,gnucash
Author: Kirill Fertikov
Author-email: kirill.fertikov@gmail.com
Requires-Python: >=3.12,<4.0
Classifier: Development Status :: 4 - Beta
Classifier: Intended Audience :: End Users/Desktop
Classifier: License :: OSI Approved :: GNU General Public License v3 or later (GPLv3+)
Classifier: Programming Language :: Python :: 3
Classifier: Programming Language :: Python :: 3.12
Classifier: Programming Language :: Python :: 3.13
Classifier: Topic :: Office/Business :: Financial :: Investment
Requires-Dist: countrynames
Requires-Dist: diskcache
Requires-Dist: pycountry
Requires-Dist: requests
Requires-Dist: yfinance
Project-URL: Bug Reports, https://github.com/fertkir/portfolio-allocation/issues
Project-URL: Repository, https://github.com/fertkir/portfolio-allocation
